src/__init__.py
src/cli.py
src/db.py
src/google_oauth.py
src/google_sheets.py
src/models.py
src/routes.py
src/server.py
src/ui/index.html
src/ui/vite.svg
src/ui/assets/index-3d95e4cb.css
src/ui/assets/index-f068790d.js
gateagent_gateway-0.1.6.dist-info/METADATA
gateagent_gateway-0.1.6.dist-info/WHEEL
gateagent_gateway-0.1.6.dist-info/entry_points.txt
gateagent_gateway-0.1.6.dist-info/top_level.txt
gateagent_gateway-0.1.6.dist-info/RECORD
