Metadata-Version: 2.4
Name: gateagent-gateway
Version: 0.1.6
Summary: Local gateway for collecting and managing agent events with Google Sheets integration
Author-email: Anshul Basia <anshulbasia@alumni.iitd.ac.in>, Siddharth Goyal <goyal.siddharth22@gmail.com>
Maintainer-email: Anshul Basia <anshulbasia@alumni.iitd.ac.in>, Siddharth Goyal <goyal.siddharth22@gmail.com>
License-Expression: MIT
Project-URL: Homepage, https://github.com/gateagent/gateway/ext
Project-URL: Repository, https://github.com/gateagent/gateway/ext
Project-URL: Issues, https://github.com/gateagent/gateway/issues
Keywords: agent,gateway,tracking,events,google-sheets,fastapi
Classifier: Development Status :: 3 - Alpha
Classifier: Intended Audience :: Developers
Classifier: Programming Language :: Python :: 3
Classifier: Programming Language :: Python :: 3.10
Classifier: Programming Language :: Python :: 3.11
Classifier: Programming Language :: Python :: 3.12
Classifier: Framework :: FastAPI
Classifier: Topic :: Software Development :: Libraries :: Python Modules
Requires-Python: >=3.8
Requires-Dist: fastapi>=0.110.0
Requires-Dist: uvicorn>=0.29.0
Requires-Dist: requests>=2.25.0
Provides-Extra: dev
Requires-Dist: pytest>=7.0.0; extra == "dev"
Requires-Dist: pytest-asyncio>=0.21.0; extra == "dev"
Requires-Dist: httpx>=0.24.0; extra == "dev"
Requires-Dist: black>=23.0.0; extra == "dev"
Requires-Dist: ruff>=0.1.0; extra == "dev"
Requires-Dist: mypy>=1.0.0; extra == "dev"
